{
  "version": "7",
  "dialect": "postgresql",
  "entries": [
    {
      "idx": 0,
      "version": "7",
      "when": 1722713588685,
      "tag": "0000_complex_silverclaw",
      "breakpoints": true
    },
    {
      "idx": 1,
      "version": "7",
      "when": 1722713776875,
      "tag": "0001_special_captain_cross",
      "breakpoints": true
    },
    {
      "idx": 2,
      "version": "7",
      "when": 1722714182358,
      "tag": "0002_giant_siren",
      "breakpoints": true
    },
    {
      "idx": 3,
      "version": "7",
      "when": 1722714745156,
      "tag": "0003_confused_eternity",
      "breakpoints": true
    },
    {
      "idx": 4,
      "version": "7",
      "when": 1722715668418,
      "tag": "0004_far_lord_hawal",
      "breakpoints": true
    }
  ]
}